akrammajli/__init__.py
akrammajli/examples.py
akrammajli/functions.py
akrammajli/plots.py
akrammajli-0.2.0.dist-info/METADATA
akrammajli-0.2.0.dist-info/WHEEL
akrammajli-0.2.0.dist-info/top_level.txt
akrammajli-0.2.0.dist-info/RECORD
