Metadata-Version: 2.4
Name: AkramMajli
Version: 0.2.0
Summary: A Python library with examples, functions, and plots.
Home-page: https://example.com
Author: Akram Majli
Author-email: akalm1900@gmail.com
License: MIT
Classifier: Programming Language :: Python :: 3
Classifier: License :: OSI Approved :: MIT License
Classifier: Operating System :: OS Independent
Requires-Dist: matplotlib
Dynamic: author
Dynamic: author-email
Dynamic: classifier
Dynamic: description
Dynamic: description-content-type
Dynamic: home-page
Dynamic: license
Dynamic: requires-dist
Dynamic: summary
